PythonCK/__init__.py
PythonCK/ioutils.py
PythonCK/itertools.py
PythonCK/stringutils.py
PythonCK/decorators/__init__.py
PythonCK/decorators/cache_to_file.py
PythonCK/decorators/decorators.py
PythonCK/decorators/lazy.py
PythonCK/decorators/meta.py
PythonCK/decorators/safe_makedir.py
PythonCK/decorators/shelves.py
PythonCK/logging/__init__.py
PythonCK/logging/conf.ini
PythonCK/logging/conf.yaml
PythonCK/logging/filters.py
PythonCK/logging/handlers.py
PythonCK/logging/logger.py
PythonCK/logging/utils.py
PythonCK-1.0.3.dist-info/LICENSE.txt
PythonCK-1.0.3.dist-info/METADATA
PythonCK-1.0.3.dist-info/RECORD
PythonCK-1.0.3.dist-info/WHEEL
PythonCK-1.0.3.dist-info/pbr.json
PythonCK-1.0.3.dist-info/top_level.txt
