Metadata-Version: 2.1
Name: PythonCK
Version: 1.0.3
Summary: Collection of utilities & helper functions.
Home-page: https://gitlab.com/ckhurewa/pythonck
Author: Chitsanu Khurewathanakul
Author-email: chitsanu.khurewathanakul@gmail.com
License: GNU GPLv3
Platform: unix
Classifier: Development Status :: 4 - Beta
Classifier: Environment :: Console
Classifier: Intended Audience :: Developers
Classifier: Intended Audience :: Information Technology
Classifier: Operating System :: OS Independent
Classifier: Programming Language :: Python :: 2.7
Classifier: Programming Language :: Python :: 3.7
Classifier: Topic :: Utilities
